domdf_spreadsheet_tools/__init__.py
domdf_spreadsheet_tools/py.typed
domdf_spreadsheet_tools-0.2.0.dist-info/LICENSE
domdf_spreadsheet_tools-0.2.0.dist-info/METADATA
domdf_spreadsheet_tools-0.2.0.dist-info/WHEEL
domdf_spreadsheet_tools-0.2.0.dist-info/entry_points.txt
domdf_spreadsheet_tools-0.2.0.dist-info/RECORD
