Metadata-Version: 2.2
Name: domdf-spreadsheet-tools
Version: 0.2.0
Summary: Tools for creating and formatting spreadsheets with Python and OpenPyXL 🐍 🛠️
Author-email: Dominic Davis-Foster <dominic@davis-foster.co.uk>
License: LGPL-3.0-or-later
Keywords: excel,openpyxl,spreadsheets,utilities
Home-page: https://github.com/domdfcoding/domdf_spreadsheet_tools
Project-URL: Issue Tracker, https://github.com/domdfcoding/domdf_spreadsheet_tools/issues
Project-URL: Source Code, https://github.com/domdfcoding/domdf_spreadsheet_tools
Project-URL: Documentation, https://domdf-spreadsheet-tools.readthedocs.io/en/latest
Platform: Windows
Platform: macOS
Platform: Linux
Classifier: Development Status :: 4 - Beta
Classifier: Intended Audience :: Developers
Classifier: License :: OSI Approved :: GNU Lesser General Public License v3 or later (LGPLv3+)
Classifier: Operating System :: OS Independent
Classifier: Programming Language :: Python
Classifier: Programming Language :: Python :: 3 :: Only
Classifier: Programming Language :: Python :: 3.6
Classifier: Programming Language :: Python :: 3.7
Classifier: Programming Language :: Python :: 3.8
Classifier: Programming Language :: Python :: 3.9
Classifier: Programming Language :: Python :: 3.10
Classifier: Programming Language :: Python :: Implementation :: CPython
Classifier: Programming Language :: Python :: Implementation :: PyPy
Classifier: Topic :: Software Development :: Libraries :: Python Modules
Classifier: Typing :: Typed
Requires-Python: >=3.6
Requires-Dist: domdf-python-tools>=1.7.0
Requires-Dist: openpyxl>=2.6.0
